zixi_api/ZixiBroadcaster.py
zixi_api/__init__.py
zixi_api-0.0.1.dist-info/METADATA
zixi_api-0.0.1.dist-info/RECORD
zixi_api-0.0.1.dist-info/WHEEL
zixi_api-0.0.1.dist-info/top_level.txt
