Metadata-Version: 2.1
Name: zixi-api
Version: 0.0.1
Summary: Python-based Zixi API wrapper
Home-page: https://github.com/jfining/zixi-api
Author: James Fining
Author-email: jfining@gmail.com
License: UNKNOWN
Platform: UNKNOWN
Classifier: Programming Language :: Python :: 2.7
Classifier: License :: OSI Approved :: Apache Software License
Classifier: Operating System :: OS Independent
Requires-Dist: requests (>=2.18.4)
